<?xml version="1.0"?>
<!DOCTYPE hibernate-mapping PUBLIC "-//Hibernate/Hibernate Mapping DTD 3.0//EN"
"http://www.hibernate.org/dtd/hibernate-mapping-3.0.dtd">
<!-- Generated Mar 7, 2018 6:20:41 PM by Hibernate Tools 4.3.1 -->
<hibernate-mapping>
    <class name="com.daisyit.entity.Catering" table="CATERING" catalog="NSRP_CATER" optimistic-lock="version">
        <composite-id name="id" class="com.daisyit.entity.CateringId">
            <key-property name="staffId" type="string">
                <column name="STAFF_ID" length="12" />
            </key-property>
            <key-property name="mealTtme" type="string">
                <column name="MEAL_TTME" length="2" />
            </key-property>
            <key-property name="caterDate" type="date">
                <column name="CATER_DATE" length="10" />
            </key-property>
        </composite-id>
        <property name="mealId" type="string">
            <column name="MEAL_ID" length="2" not-null="true" />
        </property>
        <property name="zoneSymb" type="string">
            <column name="ZONE_SYMB" length="4" />
        </property>
        <property name="shift" type="string">
            <column name="SHIFT" length="2" />
        </property>
        <property name="catered" type="boolean">
            <column name="CATERED" not-null="true" />
        </property>
        <property name="caterTime" type="string">
            <column name="CATER_TIME" length="5" not-null="true" />
        </property>
        <property name="status" type="boolean">
            <column name="STATUS" not-null="true" />
        </property>
        <property name="wsId" type="string">
            <column name="WS_ID" length="3" />
        </property>
        <property name="userId" type="string">
            <column name="USER_ID" length="20" />
        </property>
        <property name="openDate" type="date">
            <column name="OPEN_DATE" length="10" />
        </property>
        <property name="modiDate" type="timestamp">
            <column name="MODI_DATE" length="19" />
        </property>
    </class>
</hibernate-mapping>
